aineko/__init__.py
aineko/__main__.py
aineko/cli/__init__.py
aineko/cli/create_pipeline.py
aineko/cli/docker_cli_wrapper.py
aineko/cli/dream.py
aineko/cli/kafka_cli_wrapper.py
aineko/cli/run.py
aineko/cli/visualize.py
aineko/config.py
aineko/core/__init__.py
aineko/core/config_loader.py
aineko/core/dataset.py
aineko/core/deploy_config_loader.py
aineko/core/node.py
aineko/core/node_manager.py
aineko/core/runner.py
aineko/datasets/__init__.py
aineko/datasets/kafka.py
aineko/models/__init__.py
aineko/models/config_schema.py
aineko/models/dataset_config_schema.py
aineko/models/deploy_config_schema.py
aineko/models/deploy_config_schema_internal.py
aineko/models/project_config_schema.py
aineko/models/validations.py
aineko/py.typed
aineko/templates/README.md
aineko/templates/__init__.py
aineko/templates/first_aineko_pipeline/__init__.py
aineko/templates/first_aineko_pipeline/cookiecutter.json
aineko/templates/first_aineko_pipeline/hooks/__init__.py
aineko/templates/first_aineko_pipeline/hooks/post_gen_project.py
aineko/templates/first_aineko_pipeline/hooks/pre_gen_project.py
aineko/templates/first_aineko_pipeline/hooks/utils.py
aineko/templates/first_aineko_pipeline/{{cookiecutter.project_slug}}/.gitignore
aineko/templates/first_aineko_pipeline/{{cookiecutter.project_slug}}/README.md
aineko/templates/first_aineko_pipeline/{{cookiecutter.project_slug}}/conf/pipeline.yml
aineko/templates/first_aineko_pipeline/{{cookiecutter.project_slug}}/deploy.yml
aineko/templates/first_aineko_pipeline/{{cookiecutter.project_slug}}/pyproject.toml
aineko/templates/first_aineko_pipeline/{{cookiecutter.project_slug}}/tests/__init__.py
aineko/templates/first_aineko_pipeline/{{cookiecutter.project_slug}}/tests/conftest.py
aineko/templates/first_aineko_pipeline/{{cookiecutter.project_slug}}/tests/test_nodes.py
aineko/templates/first_aineko_pipeline/{{cookiecutter.project_slug}}/{{cookiecutter.project_slug}}/__init__.py
aineko-0.4.0.dist-info/LICENSE
aineko-0.4.0.dist-info/METADATA
aineko-0.4.0.dist-info/WHEEL
aineko-0.4.0.dist-info/entry_points.txt
aineko-0.4.0.dist-info/RECORD
