Metadata-Version: 2.1
Name: aineko
Version: 0.4.0
Summary: Aineko, a data integration framework.
Home-page: https://aineko.dev
License: Apache-2.0
Author: Convex Labs
Author-email: engineering-admins@convexlabs.xyz
Requires-Python: >=3.8,<3.12
Classifier: Development Status :: 4 - Beta
Classifier: License :: OSI Approved :: Apache Software License
Classifier: Natural Language :: English
Classifier: Programming Language :: Python :: 3
Classifier: Programming Language :: Python :: 3.8
Classifier: Programming Language :: Python :: 3.9
Classifier: Programming Language :: Python :: 3.10
Classifier: Programming Language :: Python :: 3.11
Classifier: Typing :: Typed
Requires-Dist: PyYAML (>=6.0.1,<7.0.0)
Requires-Dist: click (>=8.1.7,<9.0.0)
Requires-Dist: confluent-kafka (>=2.2.0,<2.3.0)
Requires-Dist: cookiecutter (>=2.4.0,<3.0.0)
Requires-Dist: pydantic (>=2.5)
Requires-Dist: pygithub (>=2.1.1,<2.2.0)
Requires-Dist: ray[default] (>=2.9.0,<3.0.0)
Project-URL: Documentation, https://docs.aineko.dev
Project-URL: Repository, https://github.com/aineko-dev/aineko
